formpy/__init__.py
formpy/formpy.py
Formpy-0.0.2.dist-info/LICENSE
Formpy-0.0.2.dist-info/METADATA
Formpy-0.0.2.dist-info/WHEEL
Formpy-0.0.2.dist-info/top_level.txt
Formpy-0.0.2.dist-info/RECORD
